quest/LICENSE
quest/__init__.py
quest/__main__.py
quest/example.log
quest/paths.py
quest/resources.qrc
quest/resources_rc.py
quest/.streamlit/config.toml
quest/app/__init__.py
quest/app/empty_file.txt
quest/app/about_pages/__init__.py
quest/app/about_pages/about_drop.py
quest/app/about_pages/about_it.py
quest/app/about_pages/ui/Qt6Core.dll
quest/app/about_pages/ui/__init__.py
quest/app/about_pages/ui/about_class.ui
quest/app/about_pages/ui/about_stack.ui
quest/app/about_pages/ui/ui_about_class.py
quest/app/about_pages/ui/ui_about_stack.py
quest/app/data_vis/__init__.py
quest/app/data_vis/data_view.py
quest/app/data_vis/ui/__init__.py
quest/app/data_vis/ui/data_vis.ui
quest/app/data_vis/ui/ui_data_vis.py
quest/app/home_page/__init__.py
quest/app/home_page/front_end.py
quest/app/home_page/home_back_end.py
quest/app/home_page/home_page.py
quest/app/home_page/ui/Qt6Core.dll
quest/app/home_page/ui/__init__.py
quest/app/home_page/ui/app_template.ui
quest/app/home_page/ui/empty
quest/app/home_page/ui/home_page.ui
quest/app/home_page/ui/ui_app_template.py
quest/app/home_page/ui/ui_home_page.py
quest/app/splash_screen/__init__.py
quest/app/splash_screen/splash_load.py
quest/app/splash_screen/ui/Qt6Core.dll
quest/app/splash_screen/ui/__init__.py
quest/app/splash_screen/ui/splash.ui
quest/app/splash_screen/ui/ui_splash.py
quest/app/tools/__init__.py
quest/app/tools/pop_down.py
quest/app/tools/env_delete/__init__.py
quest/app/tools/env_delete/delete_env.py
quest/app/tools/reqs/__init__.py
quest/app/tools/reqs/energy_reqs.txt
quest/app/tools/reqs/planning_reqs.txt
quest/app/tools/reqs/viz_requirements.txt
quest/app/tools/script_files/__init__.py
quest/app/tools/script_files/afr.bat
quest/app/tools/script_files/afr.sh
quest/app/tools/script_files/btm.bat
quest/app/tools/script_files/btm.sh
quest/app/tools/script_files/energy.bat
quest/app/tools/script_files/energy.sh
quest/app/tools/script_files/eval.bat
quest/app/tools/script_files/eval.sh
quest_snl-2.0.dev2.dist-info/licenses/LICENSE
quest_snl-2.0.dev2.dist-info/METADATA
quest_snl-2.0.dev2.dist-info/WHEEL
quest_snl-2.0.dev2.dist-info/entry_points.txt
quest_snl-2.0.dev2.dist-info/top_level.txt
quest_snl-2.0.dev2.dist-info/RECORD
