Metadata-Version: 2.4
Name: quest-snl
Version: 2.0.dev2
Summary: Sandia National Laboratories Energy Storage Application Platform
Home-page: https://github.com/sandialabs/snl-quest.git
Author: Sandia National Laboratories
Maintainer-email: Sandia National Laboratories <tunguy@sandia.gov>
License-Expression: BSD-3-Clause
Requires-Python: >=3.6, <3.11
License-File: LICENSE
Requires-Dist: PySide6==6.5.2
Requires-Dist: pandas==2.2.1
Requires-Dist: streamlit==1.33.0
Requires-Dist: openai==0.28.1
Requires-Dist: configparser==6.0.1
Requires-Dist: matplotlib==3.8.3
Requires-Dist: geopandas==0.14.3
Requires-Dist: psutil==5.9.0
Requires-Dist: GitPython==3.1.43
Dynamic: home-page
Dynamic: license-file
Dynamic: requires-python
